AUTHORS
INSTALL
LICENSE
MANIFEST.in
NOTICE
README
requirements.txt
setup.cfg
setup.py
docs/Makefile
docs/conf.py
docs/configuration.rst
docs/faq.rst
docs/index.rst
docs/installation.rst
docs/introduction.rst
docs/make.bat
docs/usage.rst
src/django_email_change.egg-info/PKG-INFO
src/django_email_change.egg-info/SOURCES.txt
src/django_email_change.egg-info/dependency_links.txt
src/django_email_change.egg-info/top_level.txt
src/email_change/__init__.py
src/email_change/admin.py
src/email_change/forms.py
src/email_change/models.py
src/email_change/settings.py
src/email_change/signal_cb.py
src/email_change/tests.py
src/email_change/urls.py
src/email_change/utils.py
src/email_change/views.py
src/email_change/locale/el/LC_MESSAGES/django.mo
src/email_change/locale/el/LC_MESSAGES/django.po
src/email_change/templates/email_change/base.html
src/email_change/templates/email_change/email_change_complete.html
src/email_change/templates/email_change/email_change_form.html
src/email_change/templates/email_change/email_verification_sent.html
src/email_change/templates/email_change/email_verify.html
src/email_change/templates/email_change/emails/verification_email_message.html
src/email_change/templates/email_change/emails/verification_email_subject.html